cli.py
core/__init__.py
core/portfolio.py
crypto_tracker_cli-0.1.0.dist-info/licenses/LICENSE
scheduler/__init__.py
scheduler/runner.py
services/__init__.py
services/coingecko_client.py
services/html_fallback.py
storage/__init__.py
storage/json_store.py
utils/__init__.py
utils/formatting.py
utils/lock.py
utils/logging.py
utils/timeutils.py
crypto_tracker_cli-0.1.0.dist-info/METADATA
crypto_tracker_cli-0.1.0.dist-info/WHEEL
crypto_tracker_cli-0.1.0.dist-info/entry_points.txt
crypto_tracker_cli-0.1.0.dist-info/top_level.txt
crypto_tracker_cli-0.1.0.dist-info/RECORD
