Metadata-Version: 2.4
Name: crypto-tracker-cli
Version: 0.1.0
Summary: Command-line crypto tracker with CoinGecko, snapshots, and a daemon.
Requires-Python: >=3.10
License-File: LICENSE
Requires-Dist: requests
Requires-Dist: beautifulsoup4
Requires-Dist: rich
Requires-Dist: apscheduler
Dynamic: license-file
